codevolution__docker_utils/__init__.py
codevolution__docker_utils/docker_compose_down.py
codevolution__docker_utils/docker_compose_pull_all.py
codevolution__docker_utils/docker_compose_pull_restart.py
codevolution__docker_utils/docker_compose_restart.py
codevolution__docker_utils/library.py
codevolution_docker_utils-0.1.dist-info/METADATA
codevolution_docker_utils-0.1.dist-info/WHEEL
codevolution_docker_utils-0.1.dist-info/top_level.txt
codevolution_docker_utils-0.1.dist-info/RECORD
