Metadata-Version: 2.1
Name: codevolution-docker-utils
Version: 0.1
Requires-Dist: PyYAML
